{
   "topic" : "MO",
   "sources" : [
	  "http://thesaurus.com/browse/movement",
      "http://makememusical.blogspot.com/2011/01/101-movement-words-fantastic-list-for.html"
   ],
   "language" : "english",
   "title" : "Movement Words",
   "phrases" : {
      "A" : [],
      "S" : [],
      "D" : [],
      "P" : [],
      "I" : [],
      "E" : [],
      "U" : [
         "bear-walk (dinosaur walk)",
         "waltz run",
         "step hop",
         "crab walk"
      ]
   },
   "full" : "movement",
   "words" : {
      "A" : [],
      "S" : [],
      "D" : [],
      "P" : [
         "leap",
         "jump",
         "roll",
         "snake",
         "creep",
         "crawl",
         "wriggle",
         "grow",
         "dash",
         "drive",
         "move",
         "zigzag",
         "slide",
         "waltz",
         "hop",
         "climb",
         "gallop",
         "tumble",
         "skate",
         "march",
         "stomp",
         "polka",
         "shuffle",
         "waddle",
         "trip",
         "flip",
         "moonwalk",
         "grapevine",
         "cat-walk",
         "scamper",
         "prance",
         "slither",
         "schottische",
         "two-step",
         "scoot",
         "push",
         "pull",
         "rock",
         "balance",
         "shake",
         "float",
         "duck",
         "dodge",
         "jab",
         "poke",
         "shove",
         "carve",
         "mold",
         "freeze",
         "wiggle",
         "turn",
         "fall",
         "straighten",
         "strike",
         "chop",
         "spin",
         "kick",
         "punch",
         "hit",
         "wring",
         "tickle",
         "hug",
         "hang",
         "sway",
         "open",
         "close",
         "flap",
         "pluck",
         "tap",
         "grab",
         "wrap",
         "flick",
         "pose",
         "burst",
         "glide",
         "shrug",
         "dig"
      ],
      "I" : [],
      "E" : [],
      "U" : []
   }
}
